<dataStore>
  <id>DataStoreInfoImpl--60a33765:13d8635fa2b:-7ffb</id>
  <name>catamidb</name>
  <type>PostGIS</type>
  <enabled>true</enabled>
  <workspace>
    <id>WorkspaceInfoImpl--60a33765:13d8635fa2b:-7ffd</id>
  </workspace>
  <connectionParameters>
    <entry key="port">5432</entry>
    <entry key="passwd">qwer789ASDF456zxcv123</entry>
    <entry key="dbtype">postgis</entry>
    <entry key="host">127.0.0.1</entry>
    <entry key="user">pocock</entry>
    <entry key="database">catamidb</entry>
    <entry key="namespace">http://catami</entry>
  </connectionParameters>
  <__default>false</__default>
</dataStore>
